{
  "nombre": "Costas F\u00f3siles Elevadas - Chile Norte",
  "coordenadas": {
    "lat_center": -27.85,
    "lon_center": -70.65,
    "lat_min": -27.917373338124328,
    "lat_max": -27.782626661875675,
    "lon_min": -70.65241915038149,
    "lon_max": -70.64758084961852
  },
  "timestamp": "2026-01-29T15:38:52.216103",
  "clasificacion": "ZONA HABITABLE - Paisaje cultural difuso",
  "comparacion_atacama": {
    "atacama_ess": 0.477,
    "costa_ess": 0.4834237463887105,
    "diferencia": -0.006423746388710516,
    "ruido_costero": "minimo"
  },
  "metricas": {
    "ess_superficial": 0.0331532590245465,
    "ess_volumetrico": 0.4834237463887105,
    "ess_temporal": 0.4834237463887105,
    "coherencia_3d": 0.5165762536112896,
    "persistencia_temporal": 0.35,
    "densidad_arqueologica_m3": 0.16673612530032794
  },
  "cobertura": {
    "superficial": {
      "successful": 1,
      "total": 5,
      "percentage": 20.0
    },
    "subsuperficial": {
      "successful": 2,
      "total": 3,
      "percentage": 66.66666666666666
    },
    "profundo": {
      "successful": 0,
      "total": 1,
      "percentage": 0.0
    }
  },
  "tas": {
    "tas_score": 0.4408803453583882,
    "ndvi_persistence": 0.0,
    "thermal_stability": 0.9890424641851381,
    "sar_coherence": 0.5766704244113872,
    "stress_frequency": 0.0,
    "temporal_scale": "long",
    "years_analyzed": 26,
    "sensors_used": [
      "landsat_thermal",
      "sentinel_1_sar"
    ],
    "interpretation": "Firma arqueol\u00f3gica temporal D\u00c9BIL. Alta estabilidad t\u00e9rmica (posible masa enterrada).",
    "confidence": 0.9
  },
  "dil": {
    "estimated_depth_m": 5.89636,
    "confidence": 0.32481799999999994,
    "confidence_level": "low",
    "sar_coherence_loss": 0.99896,
    "thermal_inertia": 1.0,
    "subsurface_moisture": 0.0,
    "topographic_anomaly": 0.0,
    "dil_score": 0.6496359999999999,
    "sensors_used": [
      "sentinel_1_sar",
      "landsat_thermal"
    ],
    "inference_method": "multi_source_coherent",
    "interpretation": "Profundidad inferida PROFUNDA (5.9m). Baja confianza en inferencia (se\u00f1ales d\u00e9biles). P\u00e9rdida de coherencia SAR detectada (cambio subsuperficial). Alta inercia t\u00e9rmica (posible masa enterrada).",
    "archaeological_relevance": 0.10550673312399995
  }
}